haxmas_day_9_dragonsenseiguy/__init__.py
haxmas_day_9_dragonsenseiguy/main.py
haxmas_day_9_dragonsenseiguy-0.0.1.dist-info/METADATA
haxmas_day_9_dragonsenseiguy-0.0.1.dist-info/WHEEL
haxmas_day_9_dragonsenseiguy-0.0.1.dist-info/entry_points.txt
haxmas_day_9_dragonsenseiguy-0.0.1.dist-info/licenses/LICENSE
haxmas_day_9_dragonsenseiguy-0.0.1.dist-info/RECORD
