Metadata-Version: 2.4
Name: haxmas_day_9_dragonsenseiguy
Version: 0.0.1
License-File: LICENSE
Requires-Dist: textual
